{
  "autoEnabled": true,
  "liveIntervalMin": 10,
  "normalIntervalMin": 180,
  "lastRunTime": 1782083823664,
  "nextRunTime": 1782084423664,
  "currentMode": "LIVE",
  "logs": [
    "[09:20:31 22/6/2026] [Match Scraper] Cào tin Uruguay vs Cape Verde Islands (ID: sm-19609178, Chế độ: LIVE, Chu kỳ: 1m) -> Thành công",
    "[09:20:31 22/6/2026] [Match Scraper] Cào tin Uruguay vs Cape Verde Islands (ID: sm-19609178, Chế độ: LIVE, Chu kỳ: 1m) -> Thành công",
    "[09:20:31 22/6/2026] [Match Scraper] Cào tin Uruguay vs Cape Verde Islands (ID: sm-19609178, Chế độ: LIVE, Chu kỳ: 1m) -> Thành công",
    "[09:20:31 22/6/2026] [Match Scraper] Cào tin Uruguay vs Cape Verde Islands (ID: sm-19609178, Chế độ: LIVE, Chu kỳ: 1m) -> Thành công",
    "[09:20:31 22/6/2026] [Match Scraper] Cào tin Uruguay vs Cape Verde Islands (ID: sm-19609178, Chế độ: LIVE, Chu kỳ: 1m) -> Thành công",
    "[09:20:31 22/6/2026] [Match Scraper] Cào tin Uruguay vs Cape Verde Islands (ID: sm-19609178, Chế độ: LIVE, Chu kỳ: 1m) -> Thành công",
    "[09:20:30 22/6/2026] [Match Scraper] Cào tin Uruguay vs Cape Verde Islands (ID: sm-19609178, Chế độ: LIVE, Chu kỳ: 1m) -> Thành công",
    "[09:20:30 22/6/2026] [Match Scraper] Cào tin Uruguay vs Cape Verde Islands (ID: sm-19609178, Chế độ: LIVE, Chu kỳ: 1m) -> Thành công",
    "[09:20:30 22/6/2026] [Match Scraper] Cào tin Uruguay vs Cape Verde Islands (ID: sm-19609178, Chế độ: LIVE, Chu kỳ: 1m) -> Thành công",
    "[09:20:30 22/6/2026] [Match Scraper] Cào tin Uruguay vs Cape Verde Islands (ID: sm-19609178, Chế độ: LIVE, Chu kỳ: 1m) -> Thành công",
    "[09:19:25 22/6/2026] [Match Scraper] Cào tin Uruguay vs Cape Verde Islands (ID: sm-19609178, Chế độ: LIVE, Chu kỳ: 1m) -> Thành công",
    "[09:19:24 22/6/2026] [Match Scraper] Cào tin Uruguay vs Cape Verde Islands (ID: sm-19609178, Chế độ: LIVE, Chu kỳ: 1m) -> Thành công",
    "[09:19:24 22/6/2026] [Match Scraper] Cào tin Uruguay vs Cape Verde Islands (ID: sm-19609178, Chế độ: LIVE, Chu kỳ: 1m) -> Thành công",
    "[09:18:57 22/6/2026] [Match Scraper] Cào tin Argentina vs Austria (ID: sm-19609146, Chế độ: UPCOMING, Chu kỳ: 10m) -> Thành công",
    "[09:18:50 22/6/2026] [Match Scraper] Cào tin Argentina vs Austria (ID: sm-19609146, Chế độ: UPCOMING, Chu kỳ: 10m) -> Thành công",
    "[09:18:49 22/6/2026] [Match Scraper] Cào tin Argentina vs Austria (ID: sm-19609146, Chế độ: UPCOMING, Chu kỳ: 10m) -> Thành công",
    "[09:18:49 22/6/2026] [Match Scraper] Cào tin Argentina vs Austria (ID: sm-19609146, Chế độ: UPCOMING, Chu kỳ: 10m) -> Thành công",
    "[09:18:49 22/6/2026] [Match Scraper] Cào tin Argentina vs Austria (ID: sm-19609146, Chế độ: UPCOMING, Chu kỳ: 10m) -> Thành công",
    "[09:18:47 22/6/2026] [Match Scraper] Cào tin Argentina vs Austria (ID: sm-19609146, Chế độ: UPCOMING, Chu kỳ: 10m) -> Thành công",
    "[09:18:44 22/6/2026] [Match Scraper] Cào tin New Zealand vs Egypt (ID: sm-19609177, Chế độ: UPCOMING, Chu kỳ: 10m) -> Thành công",
    "[09:18:44 22/6/2026] [Match Scraper] Cào tin Argentina vs Austria (ID: sm-19609146, Chế độ: UPCOMING, Chu kỳ: 10m) -> Thành công",
    "[09:18:40 22/6/2026] [Match Scraper] Cào tin Argentina vs Austria (ID: sm-19609146, Chế độ: UPCOMING, Chu kỳ: 10m) -> Thành công",
    "[09:18:39 22/6/2026] [Match Scraper] Cào tin New Zealand vs Egypt (ID: sm-19609177, Chế độ: UPCOMING, Chu kỳ: 10m) -> Thành công",
    "[09:18:37 22/6/2026] [Match Scraper] Cào tin New Zealand vs Egypt (ID: sm-19609177, Chế độ: UPCOMING, Chu kỳ: 10m) -> Thành công",
    "[09:18:37 22/6/2026] [Match Scraper] Cào tin Argentina vs Austria (ID: sm-19609146, Chế độ: UPCOMING, Chu kỳ: 10m) -> Thành công",
    "[09:18:36 22/6/2026] [Match Scraper] Cào tin Argentina vs Austria (ID: sm-19609146, Chế độ: UPCOMING, Chu kỳ: 10m) -> Thành công",
    "[09:18:36 22/6/2026] [Match Scraper] Cào tin New Zealand vs Egypt (ID: sm-19609177, Chế độ: UPCOMING, Chu kỳ: 10m) -> Thành công",
    "[09:18:35 22/6/2026] [Match Scraper] Cào tin New Zealand vs Egypt (ID: sm-19609177, Chế độ: UPCOMING, Chu kỳ: 10m) -> Thành công",
    "[09:18:35 22/6/2026] [Match Scraper] Cào tin Argentina vs Austria (ID: sm-19609146, Chế độ: UPCOMING, Chu kỳ: 10m) -> Thành công",
    "[09:18:33 22/6/2026] [Match Scraper] Cào tin New Zealand vs Egypt (ID: sm-19609177, Chế độ: UPCOMING, Chu kỳ: 10m) -> Thành công"
  ],
  "matchStates": {
    "sm-19609178": {
      "lastRunTime": 1782084031814,
      "nextRunTime": 1782084091814,
      "currentIntervalMin": 1
    },
    "sm-19609162": {
      "lastRunTime": 1782081924383,
      "nextRunTime": 1782092724383,
      "currentIntervalMin": 180
    },
    "sm-19609139": {
      "lastRunTime": 1782081996224,
      "nextRunTime": 1782092796224,
      "currentIntervalMin": 180
    },
    "sm-19609161": {
      "lastRunTime": 1782081989560,
      "nextRunTime": 1782092789560,
      "currentIntervalMin": 180
    },
    "sm-19609160": {
      "lastRunTime": 1782082059481,
      "nextRunTime": 1782092859481,
      "currentIntervalMin": 180
    },
    "sm-19609143": {
      "lastRunTime": 1782082102856,
      "nextRunTime": 1782092902856,
      "currentIntervalMin": 180
    },
    "sm-19609163": {
      "lastRunTime": 1782082128500,
      "nextRunTime": 1782092928500,
      "currentIntervalMin": 180
    },
    "sm-19609145": {
      "lastRunTime": 1782082153324,
      "nextRunTime": 1782092953324,
      "currentIntervalMin": 180
    },
    "sm-19609164": {
      "lastRunTime": 1782082167408,
      "nextRunTime": 1782092967408,
      "currentIntervalMin": 180
    },
    "sm-19609166": {
      "lastRunTime": 1782082220906,
      "nextRunTime": 1782093020906,
      "currentIntervalMin": 180
    },
    "sm-19609149": {
      "lastRunTime": 1782082194548,
      "nextRunTime": 1782092994548,
      "currentIntervalMin": 180
    },
    "sm-19609167": {
      "lastRunTime": 1782082255813,
      "nextRunTime": 1782093055813,
      "currentIntervalMin": 180
    },
    "sm-19609165": {
      "lastRunTime": 1782082273077,
      "nextRunTime": 1782093073077,
      "currentIntervalMin": 180
    },
    "sm-19609168": {
      "lastRunTime": 1782082290632,
      "nextRunTime": 1782093090632,
      "currentIntervalMin": 180
    },
    "sm-19609169": {
      "lastRunTime": 1782082308359,
      "nextRunTime": 1782093108359,
      "currentIntervalMin": 180
    },
    "sm-19609170": {
      "lastRunTime": 1782082323817,
      "nextRunTime": 1782093123817,
      "currentIntervalMin": 180
    },
    "sm-19609128": {
      "lastRunTime": 1782082338349,
      "nextRunTime": 1782093138349,
      "currentIntervalMin": 180
    },
    "sm-19609134": {
      "lastRunTime": 1782082360264,
      "nextRunTime": 1782093160264,
      "currentIntervalMin": 180
    },
    "sm-19609171": {
      "lastRunTime": 1782082381500,
      "nextRunTime": 1782093181500,
      "currentIntervalMin": 180
    },
    "sm-19609172": {
      "lastRunTime": 1782082398233,
      "nextRunTime": 1782093198233,
      "currentIntervalMin": 180
    },
    "sm-19609173": {
      "lastRunTime": 1782082420789,
      "nextRunTime": 1782093220789,
      "currentIntervalMin": 180
    },
    "sm-19609176": {
      "lastRunTime": 1782082448432,
      "nextRunTime": 1782093248432,
      "currentIntervalMin": 180
    },
    "sm-19609135": {
      "lastRunTime": 1782082461209,
      "nextRunTime": 1782093261209,
      "currentIntervalMin": 180
    },
    "sm-19609174": {
      "lastRunTime": 1782082496908,
      "nextRunTime": 1782093296908,
      "currentIntervalMin": 180
    },
    "sm-19609175": {
      "lastRunTime": 1782082483643,
      "nextRunTime": 1782093283643,
      "currentIntervalMin": 180
    },
    "sm-19609142": {
      "lastRunTime": 1782082486980,
      "nextRunTime": 1782093286980,
      "currentIntervalMin": 180
    },
    "sm-19609152": {
      "lastRunTime": 1782082553725,
      "nextRunTime": 1782093353725,
      "currentIntervalMin": 180
    },
    "sm-19609177": {
      "lastRunTime": 1782083924156,
      "nextRunTime": 1782084524156,
      "currentIntervalMin": 10
    },
    "sm-19609146": {
      "lastRunTime": 1782083937117,
      "nextRunTime": 1782084537117,
      "currentIntervalMin": 10
    },
    "sm-19609179": {
      "lastRunTime": 1782082630900,
      "nextRunTime": 1782093430900,
      "currentIntervalMin": 180
    },
    "sm-19609180": {
      "lastRunTime": 1782082657730,
      "nextRunTime": 1782093457730,
      "currentIntervalMin": 180
    },
    "sm-19609181": {
      "lastRunTime": 1782082670359,
      "nextRunTime": 1782093470359,
      "currentIntervalMin": 180
    },
    "sm-19609148": {
      "lastRunTime": 1782082746904,
      "nextRunTime": 1782093546904,
      "currentIntervalMin": 180
    },
    "sm-19609183": {
      "lastRunTime": 1782082696757,
      "nextRunTime": 1782093496757,
      "currentIntervalMin": 180
    },
    "sm-19609151": {
      "lastRunTime": 1782082748376,
      "nextRunTime": 1782093548376,
      "currentIntervalMin": 180
    },
    "sm-19609182": {
      "lastRunTime": 1782082766620,
      "nextRunTime": 1782093566620,
      "currentIntervalMin": 180
    },
    "sm-19609129": {
      "lastRunTime": 1782082784571,
      "nextRunTime": 1782093584571,
      "currentIntervalMin": 180
    },
    "sm-19609186": {
      "lastRunTime": 1782082801294,
      "nextRunTime": 1782093601294,
      "currentIntervalMin": 180
    },
    "sm-19609132": {
      "lastRunTime": 1782082825548,
      "nextRunTime": 1782093625548,
      "currentIntervalMin": 180
    },
    "sm-19609187": {
      "lastRunTime": 1782082846662,
      "nextRunTime": 1782093646662,
      "currentIntervalMin": 180
    },
    "sm-19609184": {
      "lastRunTime": 1782082861133,
      "nextRunTime": 1782093661133,
      "currentIntervalMin": 180
    },
    "sm-19609185": {
      "lastRunTime": 1782082878715,
      "nextRunTime": 1782093678715,
      "currentIntervalMin": 180
    },
    "sm-19609136": {
      "lastRunTime": 1782082891515,
      "nextRunTime": 1782093691515,
      "currentIntervalMin": 180
    },
    "sm-19609191": {
      "lastRunTime": 1782082914081,
      "nextRunTime": 1782093714081,
      "currentIntervalMin": 180
    },
    "sm-19609137": {
      "lastRunTime": 1782082903667,
      "nextRunTime": 1782093703667,
      "currentIntervalMin": 180
    },
    "sm-19609190": {
      "lastRunTime": 1782082907011,
      "nextRunTime": 1782093707011,
      "currentIntervalMin": 180
    },
    "sm-19609188": {
      "lastRunTime": 1782082936905,
      "nextRunTime": 1782093736905,
      "currentIntervalMin": 180
    },
    "sm-19609189": {
      "lastRunTime": 1782082967155,
      "nextRunTime": 1782093767155,
      "currentIntervalMin": 180
    },
    "sm-19609144": {
      "lastRunTime": 1782082985788,
      "nextRunTime": 1782093785788,
      "currentIntervalMin": 180
    },
    "sm-19609195": {
      "lastRunTime": 1782082999799,
      "nextRunTime": 1782093799799,
      "currentIntervalMin": 180
    },
    "sm-19609141": {
      "lastRunTime": 1782082994139,
      "nextRunTime": 1782093794139,
      "currentIntervalMin": 180
    },
    "sm-19609194": {
      "lastRunTime": 1782082997135,
      "nextRunTime": 1782093797135,
      "currentIntervalMin": 180
    },
    "sm-19609192": {
      "lastRunTime": 1782083069635,
      "nextRunTime": 1782093869635,
      "currentIntervalMin": 180
    },
    "sm-19609193": {
      "lastRunTime": 1782083126695,
      "nextRunTime": 1782093926695,
      "currentIntervalMin": 180
    },
    "sm-19609150": {
      "lastRunTime": 1782083155673,
      "nextRunTime": 1782093955673,
      "currentIntervalMin": 180
    },
    "sm-19609199": {
      "lastRunTime": 1782083143467,
      "nextRunTime": 1782093943467,
      "currentIntervalMin": 180
    },
    "sm-19609147": {
      "lastRunTime": 1782083225441,
      "nextRunTime": 1782094025441,
      "currentIntervalMin": 180
    },
    "sm-19609196": {
      "lastRunTime": 1782083206981,
      "nextRunTime": 1782094006981,
      "currentIntervalMin": 180
    },
    "sm-19609197": {
      "lastRunTime": 1782083209847,
      "nextRunTime": 1782094009847,
      "currentIntervalMin": 180
    },
    "sm-19609198": {
      "lastRunTime": 1782083306738,
      "nextRunTime": 1782094106738,
      "currentIntervalMin": 180
    }
  }
}